crp/__init__.py
crp/__main__.py
crp/attribution.py
crp/cache.py
crp/concepts.py
crp/graph.py
crp/helper.py
crp/hooks.py
crp/image.py
crp/maximization.py
crp/statistics.py
crp/visualization.py
zennit_crp-0.6.0.dist-info/LICENSE
zennit_crp-0.6.0.dist-info/METADATA
zennit_crp-0.6.0.dist-info/WHEEL
zennit_crp-0.6.0.dist-info/top_level.txt
zennit_crp-0.6.0.dist-info/RECORD
