Metadata-Version: 2.1
Name: zennit-crp
Version: 0.6.0
Summary: Concept Relevance Propagation and Relevance Maximization
Home-page: https://github.com/rachtibat/zennit-crp
Author: Reduan Achtibat
License: BSD 3-Clause Clear License
Classifier: Development Status :: 1 - Planning
Classifier: Intended Audience :: Science/Research
Classifier: Programming Language :: Python :: 3.8
Classifier: Programming Language :: Python :: 3.9
Requires-Python: >=3.8
License-File: LICENSE
Requires-Dist: zennit (<=0.4.6)
Requires-Dist: torch (>=1.7.0)
Requires-Dist: tqdm
Requires-Dist: matplotlib
Provides-Extra: fast_img
Requires-Dist: Pillow-SIMD ; extra == 'fast_img'
